{
  "author": ["AGSCogs"],
  "description": "Monitors multiple game server realms and posts status updates when they go online or offline.",
  "disabled": false,
  "end_user_data_statement": "This cog does not store data about users.",
  "hidden": false,
  "install_msg": "Thank you for installing AGSServerStatus! Use `[p]serverstatus` to manage monitored servers.",
  "min_bot_version": "3.5.0",
  "min_python_version": [3, 9, 1],
  "permissions": [],
  "required_cogs": {},
  "requirements": ["aiohttp"],
  "short": "Game Server Status Monitoring",
  "tags": ["utility", "server", "status", "monitoring"],
  "type": "COG"
}